{
  "title": "HCS Orlando Major",
  "link": "https://liquipedia.net/halo/Halo_Championship_Series/2021-22/Orlando",
  "timezone": "America/New_York",
  "streams": [
    {
      "id": "halo",
      "name": "Halo",
      "link": "https://www.twitch.tv/halo",
      "span": 1
    },
    {
      "id": "xbox",
      "name": "Xbox",
      "link": "https://www.twitch.tv/xbox",
      "span": 1
    },
    {
      "id": "red",
      "name": "HCS_Red",
      "link": "https://www.twitch.tv/hcs_red",
      "span": 1
    },
    {
      "id": "blue",
      "name": "HCS_Blue",
      "link": "https://www.twitch.tv/hcs_blue",
      "span": 1
    }
  ],
  "days": [
    {
      "date": "2022-09-23",
      "name": "Friday",
      "events": [
        {
          "time": "11:45",
          "items": [
            {
              "text": "Orlando Pre-Show",
              "span": 4,
              "textClass": "text-lg font-bold"
            }
          ]
        },
        {
          "time": "12:00",
          "items": [
            {
              "teams": ["optic",  "acend"]
            },
            {
              "teams": ["g1",  "nativeRed"]
            },
            {
              "teams": ["faze",  "chiefs"]
            },
            {
              "teams": ["quadrant",  "cintanegra"]
            }
          ]
        },
        {
          "time": "13:30",
          "items": [
            {
              "teams": ["eunited",  "ssg"]
            },
            {
              "teams": ["sentinels",  "navi"]
            },
            {
              "teams": ["cloud9",  "jlingz"]
            },
            {
              "teams": ["g2",  "cruelty"]
            }
          ]
        },
        {
          "time": "15:00",
          "items": [
            {
              "teams": ["g1",  "quadrant"]
            },
            {
              "teams": ["faze",  "acend"]
            },
            {
              "teams": ["optic",  "chiefs"]
            },
            {
              "teams": ["nativeRed",  "cintanegra"]
            }
          ]
        },
        {
          "time": "16:30",
          "items": [
            {
              "teams": ["sentinels",  "g2"]
            },
            {
              "teams": ["cloud9",  "ssg"]
            },
            {
              "teams": ["eunited",  "jlingz"]
            },
            {
              "teams": ["navi",  "cruelty"]
            }
          ]
        },
        {
          "time": "18:00",
          "items": [
            {
              "teams": ["optic",  "faze"]
            },
            {
              "teams": ["nativeRed",  "quadrant"]
            },
            {
              "teams": ["acend",  "chiefs"]
            },
            {
              "teams": ["g1",  "cintanegra"]
            }
          ]
        },
        {
          "time": "19:30",
          "items": [
            {
              "teams": ["cloud9",  "eunited"]
            },
            {
              "teams": ["g2",  "navi"]
            },
            {
              "teams": ["jlingz",  "ssg"]
            },
            {
              "teams": ["sentinels",  "cruelty"]
            }
          ]
        }
      ],
      "streams": ["halo", "xbox", "red", "blue"],
      "include": ["pools"]
    },
    {
      "date": "2022-09-24",
      "name": "Saturday",
      "events": [
        {
          "time": "13:15",
          "items": [
            {
              "text": "Orlando Pre-Show",
              "span": 4
            }
          ]
        },
        {
          "time": "13:30",
          "items": [
            {
              "teams": ["faze",  "fnatic"]
            },
            {
              "teams": ["quadrant",  "oxygen"]
            },
            {
              "teams": ["g2",  "tss"]
            },
            {
              "teams": ["cloud9",  "falling"]
            }
          ]
        },
        {
          "time": "15:00",
          "items": [
            {
              "teams": ["optic",  "fnatic"]
            },
            {
              "teams": ["eunited",  "falling"]
            },
            {
              "teams": ["sentinels",  "tss"]
            },
            {
              "teams": ["g1",  "oxygen"]
            }
          ]
        },
        {
          "time": "16:30",
          "items": [
            {
              "text": "Winners Quarterfinals",
              "teams": ["optic",  "oxygen"]
            },
            {
              "text": "Winners Quarterfinals",
              "teams": ["g1",  "faze"]
            },
            {
              "text": "Elimination Round 1",
              "teams": ["chiefs",  "proton"]
            },
            {
              "text": "Elimination Round 1",
              "teams": ["falling",  "war"]
            }
          ]
        },
        {
          "time": "18:00",
          "items": [
            {
              "text": "Winners Quarterfinals",
              "teams": ["sentinels",  "cloud9"]
            },
            {
              "text": "Winners Quarterfinals",
              "teams": ["eunited",  "g2"]
            },
            {
              "text": "Elimination Round 2"
            },
            {
              "text": "Elimination Round 2"
            }
          ]
        },
        {
          "time": "19:30",
          "items": [
            {
              "text": "Elimination Round 3",
              "teams": ["acend",  "war"]
            },
            {
              "text": "Elimination Round 3"
            },
            {
              "text": "Elimination Round 3",
              "span": 2
            }
          ]
        },
        {
          "time": "21:00",
          "items": [
            {
              "text": "Winners Semifinals"
            },
            {
              "text": "Winners Semifinals"
            },
            {
              "text": "Elmination Round 4"
            },
            {
              "text": "Elimination Round 4"
            }
          ]
        }
      ],
      "streams": ["halo", "xbox", "red", "blue"],
      "include": ["pools"]
    },
    {
      "date": "2022-09-25",
      "name": "Championship",
      "events": [
        {
          "time": "10:30",
          "items": [
            {
              "text": ""
            },
            {
              "text": ""
            },
            {
              "teams": ["g2",  "oxygen"],
              "text": "Elimination Round 5"
            },
            {
              "teams": ["g1",  "sentinels"],
              "text": "Elimination Round 5"
            }
          ]
        },
        {
          "time": "11:45",
          "items": [
            {
              "text": "Pre-Show: Halo Infinite World Premier",
              "textClass": "text-xl font-bold tracking-wide",
              "span": 4
            }
          ]
        },
        {
          "time": "12:00",
          "items": [
            {
              "text": "Throwback Throwdown",
              "span": 4,
              "textClass": "text-xl font-bold tracking-wide",
              "teams": ["triggersDown",  "instinct"]
            }
          ]
        },
        {
          "time": "12:30",
          "items": [
            {
              "text": "Elimination Quarterfinals",
              "teams": ["tbd",  "eunited"]
            },
            {
              "text": "Elimination Quarterfinals",
              "teams": ["cloud9",  "tbd"]
            },
            {
              "text": ""
            },
            {
              "text": ""
            }
          ]
        },
        {
          "time": "14:00",
          "items": [
            {
              "text": "Winners Finals",
              "teams": ["optic",  "faze"]
            },
            {
              "text": "Elimination Semifinals"
            },
            {
              "text": ""
            },
            {
              "text": ""
            }
          ]
        },
        {
          "time": "15:30",
          "items": [
            {
              "text": "Elimination Finals",
              "textClass": "text-xl font-bold tracking-wide",
              "span": 4
            }
          ]
        },
        {
          "time": "17:00",
          "items": [
            {
              "text": "Grand Finals",
              "textClass": "text-xl font-bold tracking-wide",
              "teams": ["optic",  "cloud9"],
              "span": 4
            }
          ]
        },
        {
          "time": "18:30",
          "items": [
            {
              "text": "Grand Finals Reset [if needed]",
              "textClass": "text-xl font-bold tracking-wide",
              "span": 4
            }
          ]
        }
      ],
      "streams": ["halo", "xbox", "red", "blue"],
      "include": ["pools"]
    }
  ],
  "pools": [
    {
      "name": "A",
      "teams": [
      "optic",
      "faze",
      "acend",
      "chiefs",
      "fnatic"
    ]},
    {
      "name": "B",
      "teams": [
      "g1",
      "nativeRed",
      "quadrant",
      "cintanegra",
      "oxygen"
    ]},
    {
      "name": "C",
      "teams": [
      "sentinels",
      "g2",
      "navi",
      "cruelty",
      "tss"
    ]},
    {
      "name": "D",
      "teams": [
      "cloud9",
      "eunited",
      "jlingz",
      "ssg",
      "falling"
    ]}
  ]
}