{
  "tbd": {
    "name": "TBD",
    "color": "",
    "region": null
  },
  "open": {
    "name": "Open Bracket Team",
    "color": "",
    "region": null
  },
  "acend": {
    "name": "ACEND",
    "color": "#6738ec",
    "region": "EU",
    "image": "acend.png"
  },
  "chiefs": {
    "name": "Chiefs",
    "color": "#3b96d7",
    "region": "AZ",
    "image": "chiefs.png"
  },
  "cloud9": {
    "name": "Cloud9",
    "color": "#0092df",
    "region": "NA",
    "image": "cloud9.png"
  },
  "xset": {
    "name": "XSET",
    "color": "#f40f30",
    "region": "NA",
    "image": "xset.png"
  },
  "faze": {
    "name": "FaZe Clan",
    "color": "#e43d30",
    "region": "NA",
    "image": "faze.png"
  },
  "fnatic": {
    "name": "Fnatic",
    "color": "#ff5900",
    "region": "NA",
    "image": "fnatic.png"
  },
  "navi": {
    "name": "Natus Vincere",
    "color": "#ffee00",
    "region": "EU",
    "image": "navi.png"
  },
  "optic": {
    "name": "Optic Gaming",
    "color": "#93c950",
    "region": "NA",
    "image": "optic.png"
  },
  "eunited": {
    "name": "eUnited",
    "color": "#2373b9",
    "region": "NA",
    "image": "eunited.png"
  },
  "g2": {
    "name": "G2 Esports",
    "color": "#ee3d23",
    "region": "NA",
    "image": "g2.png"
  },
  "quadrant": {
    "name": "Quadrant",
    "color": "#ccdb25",
    "region": "EU",
    "image": "quadrant.png"
  },
  "cruelty": {
    "name": "Team Cruelty",
    "color": "#8806ec",
    "region": "MX",
    "image": "cruelty.png"
  },
  "jlingz": {
    "name": "JLINGZ esports",
    "color": "#4c4c4c",
    "region": "EU",
    "image": "jlingz.png"
  },
  "pioneers": {
    "name": "Pioneers",
    "color": "#a7933d",
    "region": "NA",
    "image": "kcp.png"
  },
  "knights": {
    "name": "Pittsburgh Knights",
    "color": "#fdc00f",
    "region": "MX",
    "image": "pknights.png"
  },
  "sentinels": {
    "name": "Sentinels",
    "color": "#ce0037",
    "region": "NA",
    "image": "sentinels.png"
  },
  "oxygen": {
    "name": "Oxygen Esports",
    "color": "#01ab42",
    "region": "NA",
    "image": "oxygen.png"
  },
  "ssg": {
    "name": "Spacestation Gaming",
    "color": "#f5b21f",
    "region": "MX",
    "image": "ssg.png"
  },
  "ssgOld": {
    "name": "Spacestation Gaming",
    "color": "#f5b21f",
    "region": "NA",
    "image": "ssg.png"
  },
  "g1": {
    "name": "Gamers First",
    "color": "#eee",
    "region": "NA",
    "image": "gamers_first.png"
  },
  "complexity": {
    "name": "Complexity Gaming",
    "color": "#002b5c",
    "region": "NA",
    "image": "complexity.png"
  },
  "bbg": {
    "name": "Built By Gamers",
    "color": "#2ce3ef",
    "region": "NA",
    "image": "bbg.png"
  },
  "blackhand": {
    "name": "BLVCKHVND",
    "color": "#262626",
    "region": "EU",
    "image": "blackhand.png"
  },
  "vexed": {
    "name": "Vexed Gaming",
    "color": "#b31d20",
    "region": "EU",
    "image": "vexed.png"
  },
  "reclaimers": {
    "name": "Reclaimers",
    "color": "#42a9f3",
    "region": "EU",
    "image": "halo.png"
  },
  "scorchedHand": {
    "name": "Scorched HVND",
    "color": "#b70d0e",
    "region": "EU",
    "image": "scorched.png"
  },
  "deathrow": {
    "name": "Deathrow",
    "color": "#bc2628",
    "region": "EU",
    "image": "deathrow.png"
  },
  "diamondDogs": {
    "name": "Diamond Dogs",
    "color": "#d9de34",
    "region": "EU",
    "image": "halo.png"
  },
  "onlineWarriors": {
    "name": "Online Warriors",
    "color": "#2933f9",
    "region": "EU",
    "image": "halo.png"
  },
  "awobabobs": {
    "name": "AWOBABOBS",
    "color": "#f6c00f",
    "region": "EU",
    "image": "halo.png"
  },
  "frostbite": {
    "name": "Frostbite",
    "color": "#c9e9ec",
    "region": "EU",
    "image": "frostbite.png"
  },
  "connecting": {
    "name": "Connecting",
    "color": "#cda039",
    "region": "EU",
    "image": "connecting.png"
  },
  "lucendi": {
    "name": "Lucendi",
    "color": "#f19718",
    "region": "EU",
    "image": "lucendi.png"
  },
  "witchblades": {
    "name": "Witchblades",
    "color": "#7588e2",
    "region": "EU",
    "image": "halo.png"
  },
  "cintanegra": {
    "name": "CintaNegra Esports",
    "color": "#77cccb",
    "region": "MX",
    "image": "cintanegra.png"
  },
  "divineMind": {
    "name": "Divine Mind",
    "color": "#37f6f7",
    "region": "AZ",
    "image": "divine-mind.png"
  },
  "direWolves": {
    "name": "Dire Wolves",
    "color": "#00aa82",
    "region": "AZ",
    "image": "dire-wolves.png"
  },
  "mindfreak": {
    "name": "Mindfreak",
    "color": "#017bff",
    "region": "AZ",
    "image": "mind-freak.png"
  },
  "kitbash": {
    "name": "Kitbash",
    "color": "",
    "region": "AZ",
    "image": "halo.png"
  },
  "immunity": {
    "name": "Immunity",
    "color": "#e2e2e2",
    "region": "AZ",
    "image": "halo.png"
  },
  "noteam": {
    "name": "No Team",
    "color": "#819abf",
    "region": "MX",
    "image": "halo.png"
  },
  "native": {
    "name": "Native Gaming",
    "color": "#d21f3d",
    "region": "NA",
    "image": "native.png"
  },
  "nativeRed": {
    "name": "Native Red",
    "color": "#d21f3d",
    "region": "NA",
    "image": "native.png"
  },
  "nativeBlack": {
    "name": "Native Black",
    "color": "#33080F",
    "region": "NA",
    "image": "native.png"
  },
  "vertex": {
    "name": "VERTEX",
    "color": "#512f6c",
    "region": "AZ",
    "image": "vertex.png"
  },
  "bandits": {
    "name": "Bandits",
    "color": "#d70029",
    "region": "AZ",
    "image": "bandits.png"
  },
  "rebellion": {
    "name": "Shopify Rebellion",
    "color": "#edeceb",
    "region": "NA",
    "image": "rebellion.png"
  },
  "tss": {
    "name": "TSS Esports",
    "color": "#fef102",
    "region": "NA",
    "image": "tss.png"
  },
  "forbiddenFruit": {
    "name": "Forbidden Fruit",
    "color": "#f42d4e",
    "region": "NA",
    "image": "halo.png"
  },
  "instinct": {
    "name": "Instinct",
    "color": "#009242",
    "region": "NA",
    "image": "instinct.png"
  },
  "triggersDown": {
    "name": "Triggers Down",
    "color": "#ed1c24",
    "region": "NA",
    "image": "triggers_down.png"
  },
  "falling": {
    "name": "Falling Esports",
    "color": "#6c6b6c",
    "region": "NA",
    "image": "falling.png"
  },
  "war": {
    "name": "Team War",
    "color": "#e0b261",
    "region": "NA",
    "image": "war.png"
  },
  "proton": {
    "name": "Proton Gaming",
    "color": "#00bbce",
    "region": "NA",
    "image": "proton.png"
  },
  "altar": {
    "name": "Altar Esports",
    "color": "#e52adf",
    "region": "MX",
    "image": "altar.png"
  }
}